eesdr_tci/__init__.py
eesdr_tci/listener.py
eesdr_tci/tci.py
eesdr_tci-0.1.0.dist-info/LICENSE
eesdr_tci-0.1.0.dist-info/METADATA
eesdr_tci-0.1.0.dist-info/WHEEL
eesdr_tci-0.1.0.dist-info/top_level.txt
eesdr_tci-0.1.0.dist-info/RECORD
