Metadata-Version: 2.1
Name: eesdr-tci
Version: 0.1.0
Summary: Python package to interact with Expert Electronics SDR TCI control interface.
Author-email: "Matthew R. McDougal" <ka0s@arrl.net>
Project-URL: Homepage, https://github.com/ars-ka0s/eesdr-tci
Project-URL: Bug Tracker, https://github.com/ars-ka0s/eesdr-tci/issues
Classifier: Programming Language :: Python :: 3
Classifier: Development Status :: 4 - Beta
Classifier: Framework :: AsyncIO
Classifier: Intended Audience :: Developers
Classifier: License :: OSI Approved :: BSD License
Classifier: Operating System :: OS Independent
Classifier: Topic :: Communications :: Ham Radio
Requires-Python: >=3.8
License-File: LICENSE
Requires-Dist: websockets
